[{"__symbolic":"module","version":4,"metadata":{"PxtAppMenuLeftComponent":{"__symbolic":"class","decorators":[{"__symbolic":"call","expression":{"__symbolic":"reference","module":"@angular/core","name":"Component","line":4,"character":1},"arguments":[{"selector":"pxt-header","template":" <mat-sidenav-container class=\"example-sidenav-container\"\n                    [style.marginTop.px]=\"mobileQuery.matches ? 56 : 0\">\n                <mat-sidenav #snav [mode]=\"mobileQuery.matches ? 'over' : 'side'\"\n                  [fixedInViewport]=\"mobileQuery.matches\" fixedTopGap=\"56\">\n                <mat-nav-list>\n                    <a mat-list-item routerLink=\".\" *ngFor=\"let nav of fillerNav\">{{nav}}</a>\n                </mat-nav-list>\n                </mat-sidenav>\n  \n     <mat-sidenav-content>\n       <p *ngFor=\"let content of fillerContent\">{{content}}</p>\n     </mat-sidenav-content>\n   </mat-sidenav-container>","styles":[".example-container {\n                display: flex;\n                flex-direction: column;\n                position: absolute;\n                top: 0;\n                bottom: 0;\n                left: 0;\n                right: 0;\n              }\n              .example-is-mobile .example-toolbar {\n                position: fixed;\n                z-index: 2;\n              }\n              h1.example-app-name {\n                margin-left: 8px;\n              }\n              .example-sidenav-container {\n                flex: 1;\n              }\n              .example-is-mobile .example-sidenav-container {\n                flex: 1 0 auto;\n              }"]}]}],"members":{"__ctor__":[{"__symbolic":"constructor","parameters":[{"__symbolic":"reference","module":"@angular/core","name":"ChangeDetectorRef","line":61,"character":35},{"__symbolic":"reference","module":"@angular/cdk/layout","name":"MediaMatcher","line":61,"character":61}]}],"ngOnDestroy":[{"__symbolic":"method"}]}}}}]